markdown_escaped.py
markdown_escaped-0.0.1.dist-info/COPYING
markdown_escaped-0.0.1.dist-info/METADATA
markdown_escaped-0.0.1.dist-info/WHEEL
markdown_escaped-0.0.1.dist-info/top_level.txt
markdown_escaped-0.0.1.dist-info/RECORD
