Metadata-Version: 2.1
Name: markdown-escaped
Version: 0.0.1
Summary: A python markdown extension for add HTML escaped symbols support
Home-page: https://github.com/alberic89/markdown_escaped
Author: alberic89
Author-email: alberic89@gmx.com
License: LGPLv3
Classifier: Operating System :: OS Independent
Classifier: License :: OSI Approved :: GNU Lesser General Public License v3 (LGPLv3)
Classifier: Intended Audience :: Developers
Classifier: Programming Language :: Python
Classifier: Topic :: Text Processing :: Filters
Classifier: Topic :: Text Processing :: Markup :: HTML
License-File: COPYING
Requires-Dist: markdown (>=3.0)
